{
  "version": "1.0",
  "lastUpdated": "2025-11-06T23:29:34.413794+00:00Z",
  "stats": {
    "totalDirectories": 13,
    "totalRepos": 1,
    "avgDirectoriesPerRepo": 13.0,
    "totalListings": 118,
    "aiEnhancedDirectories": 13
  },
  "directories": {
    "chinese-american-owned-website-maintenance-in-california": {
      "repo": "offren-directories-batch-001",
      "created": "2025-11-06T23:18:32.389303+00:00Z",
      "lastUpdated": "2025-11-06T23:18:32.389303+00:00Z",
      "status": "active",
      "listingsCount": 10,
      "opportunityScore": 80,
      "aiEnhanced": true,
      "researchSources": [
        "pollinations_ai"
      ],
      "competition": "medium"
    },
    "american-indian-owned-search-engine-optimization-in-mississippi": {
      "repo": "offren-directories-batch-001",
      "created": "2025-11-06T23:20:02.106706+00:00Z",
      "lastUpdated": "2025-11-06T23:20:02.106706+00:00Z",
      "status": "active",
      "listingsCount": 10,
      "opportunityScore": 80,
      "aiEnhanced": true,
      "researchSources": [
        "pollinations_ai"
      ],
      "competition": "medium"
    },
    "american-indian-owned-janitorial-staff-in-north-carolina": {
      "repo": "offren-directories-batch-001",
      "created": "2025-11-06T23:20:56.804443+00:00Z",
      "lastUpdated": "2025-11-06T23:20:56.804443+00:00Z",
      "status": "active",
      "listingsCount": 8,
      "opportunityScore": 70,
      "aiEnhanced": true,
      "researchSources": [
        "pollinations_ai"
      ],
      "competition": "medium"
    },
    "american-indian-owned-abs-repair-in-tennessee": {
      "repo": "offren-directories-batch-001",
      "created": "2025-11-06T23:21:36.335627+00:00Z",
      "lastUpdated": "2025-11-06T23:21:36.335627+00:00Z",
      "status": "active",
      "listingsCount": 10,
      "opportunityScore": 80,
      "aiEnhanced": true,
      "researchSources": [
        "pollinations_ai"
      ],
      "competition": "medium"
    },
    "baby-boomer-owned-logistics-coordination-in-florida": {
      "repo": "offren-directories-batch-001",
      "created": "2025-11-06T23:22:41.079552+00:00Z",
      "lastUpdated": "2025-11-06T23:22:41.079552+00:00Z",
      "status": "active",
      "listingsCount": 10,
      "opportunityScore": 80,
      "aiEnhanced": true,
      "researchSources": [
        "pollinations_ai"
      ],
      "competition": "medium"
    },
    "asian-owned-dermatologists-in-louisiana": {
      "repo": "offren-directories-batch-001",
      "created": "2025-11-06T23:22:53.944280+00:00Z",
      "lastUpdated": "2025-11-06T23:22:53.944280+00:00Z",
      "status": "active",
      "listingsCount": 3,
      "opportunityScore": 50,
      "aiEnhanced": true,
      "researchSources": [
        "pollinations_ai"
      ],
      "competition": "medium"
    },
    "baby-boomer-owned-mosquito-control-in-arizona": {
      "repo": "offren-directories-batch-001",
      "created": "2025-11-06T23:23:08.785794+00:00Z",
      "lastUpdated": "2025-11-06T23:23:08.785794+00:00Z",
      "status": "active",
      "listingsCount": 10,
      "opportunityScore": 80,
      "aiEnhanced": true,
      "researchSources": [
        "pollinations_ai"
      ],
      "competition": "medium"
    },
    "american-indian-owned-wine-bars-in-michigan": {
      "repo": "offren-directories-batch-001",
      "created": "2025-11-06T23:23:48.976552+00:00Z",
      "lastUpdated": "2025-11-06T23:23:48.976552+00:00Z",
      "status": "active",
      "listingsCount": 7,
      "opportunityScore": 70,
      "aiEnhanced": true,
      "researchSources": [
        "pollinations_ai"
      ],
      "competition": "medium"
    },
    "arabic-speaking-body-wraps-in-indiana": {
      "repo": "offren-directories-batch-001",
      "created": "2025-11-06T23:26:59.027661+00:00Z",
      "lastUpdated": "2025-11-06T23:26:59.027661+00:00Z",
      "status": "active",
      "listingsCount": 10,
      "opportunityScore": 80,
      "aiEnhanced": true,
      "researchSources": [
        "pollinations_ai"
      ],
      "competition": "medium"
    },
    "asian-owned-low-vision-services-in-new-mexico": {
      "repo": "offren-directories-batch-001",
      "created": "2025-11-06T23:27:13.411469+00:00Z",
      "lastUpdated": "2025-11-06T23:27:13.411469+00:00Z",
      "status": "active",
      "listingsCount": 10,
      "opportunityScore": 80,
      "aiEnhanced": true,
      "researchSources": [
        "pollinations_ai"
      ],
      "competition": "medium"
    },
    "chinese-american-owned-robotics-instruction-in-connecticut": {
      "repo": "offren-directories-batch-001",
      "created": "2025-11-06T23:27:53.762123+00:00Z",
      "lastUpdated": "2025-11-06T23:27:53.762123+00:00Z",
      "status": "active",
      "listingsCount": 10,
      "opportunityScore": 80,
      "aiEnhanced": true,
      "researchSources": [
        "pollinations_ai"
      ],
      "competition": "medium"
    },
    "christian-owned-business-process-outsourcing-in-kentucky": {
      "repo": "offren-directories-batch-001",
      "created": "2025-11-06T23:28:55.733467+00:00Z",
      "lastUpdated": "2025-11-06T23:28:55.733467+00:00Z",
      "status": "active",
      "listingsCount": 10,
      "opportunityScore": 80,
      "aiEnhanced": true,
      "researchSources": [
        "pollinations_ai"
      ],
      "competition": "medium"
    },
    "baby-boomer-owned-equipment-repair-in-illinois": {
      "repo": "offren-directories-batch-001",
      "created": "2025-11-06T23:29:34.413794+00:00Z",
      "lastUpdated": "2025-11-06T23:29:34.413794+00:00Z",
      "status": "active",
      "listingsCount": 10,
      "opportunityScore": 80,
      "aiEnhanced": true,
      "researchSources": [
        "pollinations_ai"
      ],
      "competition": "medium"
    }
  },
  "repos": {
    "offren-directories-batch-001": {
      "created": "2025-11-06T23:18:32.389303+00:00Z",
      "directoryCount": 13,
      "status": "active",
      "sizeMB": 0.001,
      "batchNumber": 1
    }
  },
  "config": {
    "maxDirectoriesPerRepo": 100,
    "maxRepoSizeMB": 800,
    "autoCreateNewRepos": true,
    "routerUrl": "https://simpledirectree.com"
  }
}